microprobe/doc/__init__.py
microprobe/doc/api.html
microprobe/doc/copyright.html
microprobe/doc/design.html
microprobe/doc/design_code_organization.html
microprobe/doc/design_code_workflow.html
microprobe/doc/design_overview.html
microprobe/doc/design_target.html
microprobe/doc/devel.html
microprobe/doc/devel_code_style.html
microprobe/doc/devel_continuous.html
microprobe/doc/devel_contributing.html
microprobe/doc/devel_patches.html
microprobe/doc/devel_repository.html
microprobe/doc/devel_roadmap.html
microprobe/doc/devel_ticket.html
microprobe/doc/examples.html
microprobe/doc/examples_power.html
microprobe/doc/examples_riscv.html
microprobe/doc/genindex.html
microprobe/doc/index.html
microprobe/doc/index_microprobe.html
microprobe/doc/index_publications.html
microprobe/doc/license.html
microprobe/doc/microprobe.code.Synthesizer.html
microprobe/doc/microprobe.code.TraceSynthesizer.html
microprobe/doc/microprobe.code.address.Address.html
microprobe/doc/microprobe.code.address.InstructionAddress.html
microprobe/doc/microprobe.code.address.MemoryValue.html
microprobe/doc/microprobe.code.address.html
microprobe/doc/microprobe.code.bbl.Bbl.html
microprobe/doc/microprobe.code.bbl.html
microprobe/doc/microprobe.code.benchmark.Benchmark.html
microprobe/doc/microprobe.code.benchmark.BuildingBlock.html
microprobe/doc/microprobe.code.benchmark.MultiThreadedBenchmark.html
microprobe/doc/microprobe.code.benchmark.html
microprobe/doc/microprobe.code.cfg.Cfg.html
microprobe/doc/microprobe.code.cfg.html
microprobe/doc/microprobe.code.context.Context.html
microprobe/doc/microprobe.code.context.html
microprobe/doc/microprobe.code.html
microprobe/doc/microprobe.code.ins.Instruction.html
microprobe/doc/microprobe.code.ins.InstructionMemoryOperandValue.html
microprobe/doc/microprobe.code.ins.InstructionOperandValue.html
microprobe/doc/microprobe.code.ins.MicroprobeInstructionDefinition.html
microprobe/doc/microprobe.code.ins.html
microprobe/doc/microprobe.code.var.Variable.html
microprobe_doc-0.5.20250911152917.dist-info/licenses/LICENSE
microprobe_doc-0.5.20250911152917.dist-info/METADATA
microprobe_doc-0.5.20250911152917.dist-info/WHEEL
microprobe_doc-0.5.20250911152917.dist-info/top_level.txt
microprobe_doc-0.5.20250911152917.dist-info/RECORD
